ipc_worker/__init__.py
ipc_worker/ipc_shm_loader.py
ipc_worker/ipc_zmq_loader.py
ipc_worker/utils.py
ipc_worker/shm_module/__init__.py
ipc_worker/shm_module/ipc_shm.py
ipc_worker/shm_module/ipc_shm_utils.py
ipc_worker/shm_module/ipc_utils_func.py
ipc_worker/zmq_module/__init__.py
ipc_worker/zmq_module/ipc_utils_func.py
ipc_worker/zmq_module/ipc_zmq.py
ipc_worker/zmq_module/ipc_zmq_utils.py
ipc_worker-0.1.7.dist-info/LICENSE
ipc_worker-0.1.7.dist-info/METADATA
ipc_worker-0.1.7.dist-info/WHEEL
ipc_worker-0.1.7.dist-info/top_level.txt
ipc_worker-0.1.7.dist-info/RECORD
