Metadata-Version: 2.1
Name: ipc-worker
Version: 0.1.7
Summary: ipc-worker: Inter-Process Communication , muti Process Woker works by share memory or MQ.
Home-page: https://github.com/ssbuild/ipc_worker
Author: ssbuild
Author-email: 9727464@qq.com
License: Apache 2.0
Keywords: ipc-worker,ipc_worker,ipc,process worker,ipc,ipc mq,fast-ipc,process ipc
Platform: win32_AMD64
Classifier: Development Status :: 5 - Production/Stable
Classifier: Intended Audience :: Developers
Classifier: Intended Audience :: Education
Classifier: Intended Audience :: Science/Research
Classifier: License :: OSI Approved :: Apache Software License
Classifier: Programming Language :: C++
Classifier: Programming Language :: Python :: 3
Classifier: Programming Language :: Python :: 3.8
Classifier: Programming Language :: Python :: 3.9
Classifier: Programming Language :: Python :: 3.10
Classifier: Programming Language :: Python :: 3.11
Classifier: Topic :: Scientific/Engineering
Classifier: Topic :: Scientific/Engineering :: Mathematics
Classifier: Topic :: Scientific/Engineering :: Artificial Intelligence
Classifier: Topic :: Software Development
Classifier: Topic :: Software Development :: Libraries
Classifier: Topic :: Software Development :: Libraries :: Python Modules
Requires-Python: >=3, <4
Requires-Dist: termcolor
